Metadata-Version: 2.1
Name: calculator-tobade
Version: 0.0.1
Summary: A basic calculator
Home-page: https://github.com/TobAde/Calculator
Author: Oluwatobi Adeniji
Author-email: oluwatobiadeniji06@gmail.com
License: UNKNOWN
Project-URL: Bug Tracker, https://github.com/TobAde/Calculator.git/issues
Platform: UNKNOWN
Classifier: Programming Language :: Python :: 3
Classifier: License :: OSI Approved :: MIT License
Classifier: Operating System :: OS Independent
Requires-Python: >=3.6
